eme_selex/__init__.py
eme_selex/decorators.py
eme_selex/eme.py
eme_selex/hashing.py
eme_selex/readers.py
eme_selex/sequence.py
eme_selex-0.4.dist-info/LICENSE
eme_selex-0.4.dist-info/WHEEL
eme_selex-0.4.dist-info/METADATA
eme_selex-0.4.dist-info/RECORD
