Metadata-Version: 2.1
Name: eme_selex
Version: 0.4
Summary: Perform k-mer abundance analysis in DNA sequences
Author-email: Kashyap Chhatbar <kashyap.cc@gmail.com>
Requires-Dist: mmh3
Requires-Dist: biopython
Requires-Dist: pytest
Requires-Dist: testfixtures
Project-URL: Home, https://github.com/kashyapchhatbar/eme_selex
